airypi/errors.py
airypi/callback_dict.py
airypi/__init__.py
airypi/ui.py
airypi/event_loop.py
airypi/utils.py
airypi/message_queue.py
airypi/action_queue.py
airypi/monkey.py
airypi/redis_session.py
airypi/remote_obj.py
airypi/server.py
airypi/redis_queue.py
airypi/device/serial.py
airypi/device/__init__.py
airypi/device/spidev.py
airypi/device/smbus.py
airypi/device/gpio.py
airypi-0.0.1.dist-info/top_level.txt
airypi-0.0.1.dist-info/RECORD
airypi-0.0.1.dist-info/WHEEL
airypi-0.0.1.dist-info/METADATA
airypi-0.0.1.dist-info/DESCRIPTION.rst
airypi-0.0.1.dist-info/metadata.json
