Metadata-Version: 2.0
Name: airypi
Version: 0.0.1
Summary: The server libraries for airypi
Home-page: https://www.airypi.com/docs/
Author: airypi
Author-email: dev@airypi.com
License: Apache License (2.0)
Keywords: raspberry,pi,server,cloud,library,airypi,control,io,gpio,serial,smbus,spi,i2c
Platform: UNKNOWN
Classifier: Development Status :: 4 - Beta
Classifier: Topic :: Software Development :: Libraries :: Python Modules
Classifier: Programming Language :: Python :: 2.7
Classifier: License :: OSI Approved :: Apache Software License
Requires-Dist: Flask
Requires-Dist: Flask-OAuthlib
Requires-Dist: Flask-SocketIO
Requires-Dist: Jinja2
Requires-Dist: MarkupSafe
Requires-Dist: Werkzeug
Requires-Dist: gevent
Requires-Dist: gevent-socketio
Requires-Dist: gevent-websocket
Requires-Dist: greenlet
Requires-Dist: itsdangerous
Requires-Dist: oauthlib
Requires-Dist: redis
Requires-Dist: requests
Requires-Dist: wsgiref
